<?xml version="1.0" encoding="UTF-8"?>
<manifest>
	<!-- <remove-project path="external/libnfc-nci" name="platform/external/libnfc-nci" groups="pdk" /> -->

	<!-- <remove-project path="hardware/qcom/audio" /> -->
	<!-- <remove-project path="hardware/qcom/bootctrl" /> -->
	<!-- <remove-project path="hardware/qcom/bt" /> -->
	<!-- <remove-project path="hardware/qcom/camera" /> -->
	<!-- <remove-project path="hardware/qcom/display" /> -->
	<!-- <remove-project path="hardware/qcom/gps" /> -->
	<!-- <remove-project path="hardware/qcom/keymaster" /> -->
	<!-- <remove-project path="hardware/qcom/media" /> -->
	<!-- <remove-project path="hardware/qcom/wlan" /> -->
	<remove-project name="platform/hardware/qcom/audio" />
	<remove-project name="platform/hardware/qcom/bootctrl" />
	<remove-project name="platform/hardware/qcom/bt" />
	<remove-project name="platform/hardware/qcom/camera" />
	<remove-project name="platform/hardware/qcom/display" />
	<remove-project name="platform/hardware/qcom/gps" />
	<remove-project name="platform/hardware/qcom/keymaster" />
	<remove-project name="platform/hardware/qcom/media" />
	<remove-project name="platform/hardware/qcom/wlan" />
	<remove-project name="platform/hardware/ril" />
</manifest>